LICENSE
README.md
pyproject.toml
setup.cfg
setup.py
jhub_client/__init__.py
jhub_client/__main__.py
jhub_client/api.py
jhub_client/auth.py
jhub_client/cli.py
jhub_client/execute.py
jhub_client/simulate.py
jhub_client/utils.py
jhub_client.egg-info/PKG-INFO
jhub_client.egg-info/SOURCES.txt
jhub_client.egg-info/dependency_links.txt
jhub_client.egg-info/entry_points.txt
jhub_client.egg-info/requires.txt
jhub_client.egg-info/top_level.txt