Metadata-Version: 2.1
Name: jhub-client
Version: 0.1.5
Summary: Library and Client for managing, benchmarking, and interacting with jupyterhub
Home-page: https://github.com/Quansight/jhub-client
Author: Christopher Ostrouchov
Author-email: chris.ostrouchov@gmail.com
License: UNKNOWN
Keywords: jupyterhub,jupyter,benchmark
Platform: UNKNOWN
Classifier: Development Status :: 3 - Alpha
Classifier: Intended Audience :: Developers
Classifier: Topic :: Software Development :: Build Tools
Classifier: License :: OSI Approved :: BSD License
Classifier: Programming Language :: Python :: 3
Classifier: Programming Language :: Python :: 3.6
Classifier: Programming Language :: Python :: 3.7
Classifier: Programming Language :: Python :: 3.8
Classifier: Programming Language :: Python :: 3 :: Only
Provides-Extra: dev
